LICENSE
README.md
setup.py
APIDjango.egg-info/PKG-INFO
APIDjango.egg-info/SOURCES.txt
APIDjango.egg-info/dependency_links.txt
APIDjango.egg-info/top_level.txt
api_deal/__init__.py
api_deal/args.py
api_deal/error.py
api_deal/models.py
api_deal/mysql.py
api_deal/page.py
api_deal/res.py
api_deal/settings.py
api_deal/view.py
api_deal/middlewares/__init__.py
api_deal/middlewares/cors.py
api_deal/middlewares/error.py