Metadata-Version: 2.1
Name: APIDjango
Version: 1.2
Summary: django api
Home-page: https://gitee.com/songhaoi/django_api_deal.git
Author: songhao
Author-email: 173077850@qq.com
License: UNKNOWN
Platform: UNKNOWN
